{
  "cli": true,
  "dir": ".",
  "outputOnly": true,
  "no-watch": true,
  "no-sockets": true,
  "editor": true,
  "user": "jleschner",
  "basedir": "/Users/jleschner/pub/firstinthecloud",
  "pkgJson": {
    "name": "firstinthecloud.com",
    "version": "1.0.0",
    "description": "firstinthecloud.com blog using pub-server",
    "repository": "git://github.com/jldec/firstinthecloud.git",
    "main": "pub-config.js",
    "dependencies": {
      "pub-theme-pubblog": "^1.2.2",
      "pub-pkg-highlight": "^0.2.4"
    },
    "scripts": {
      "develop": "pub",
      "generate": "pub -O",
      "static": "pub -S out"
    },
    "license": "CC BY 4.0"
  },
  "pkgName": "firstinthecloud.com",
  "sources": [
    {
      "path": "markdown",
      "writable": true,
      "name": "markdown",
      "type": "FILE",
      "tmp": "/Users/jleschner/.tmp/markdown",
      "watch": {},
      "fragmentDelim": true,
      "files": [
        {
          "path": "/home.md",
          "text": "---- / ----\nname: firstinthecloud\ntemplate: home\nmultipage: 1\nimage: \n"
        },
        {
          "path": "/how-this-site-is-hosted.md",
          "text": "---- /how-this-site-is-hosted ----\ntitle: How this site is hosted\nimage:\ndate: 2017-06-24\ntemplate: post\n\n# 1st post\n\nWelcome to https://firstinthecloud.com, a blog about software in the _!cloud_.\n\n## [GitHub Pages](https://help.github.com/articles/what-is-github-pages/) and [pub-server](https://github.com/jldec/pub-server)\n\nA [git repo](https://github.com/jldec/firstinthecloud.com) is used to manage content in markdown files. Generating HTML into the `/docs` folder in the same repo makes for an easy publishing workflow.\n\n1. Write and preview locally using `pub`.\n2. When ready to publish, generate the HTML with `pub -O`.\n3. `git commit` and `git push` to make the changes live.\n\nHere are the GitHub Pages settings:  \n![Github Pages Settings](/images/gh-pages-settings.png)\n\n## [AWS Route 53](https://aws.amazon.com/route53/)\n\nThe domain name was registered with the registrar at AWS. _This was the only part of the site which required any payment._\n\n![Route 53 Domain](/images/route-53.png)\n\n## [Cloudflare](https://www.cloudflare.com)\n\nCloudflare manages the DNS name servers, SSL, [CNAME flattening](https://blog.cloudflare.com/introducing-cname-flattening-rfc-compliant-cnames-at-a-domains-root/), redirection from HTTP to HTTPS, and also serves as an additional CDN layer in front of GitHub Pages.\n\n![Cloudflare DNS](/images/cloudflare-dns.png)\n![Cloudflare Pagerule](/images/cloudflare-pagerule.png)\n\n> _!motorcycle 2x_\n"
        },
        {
          "path": "/spring-boot-101.md",
          "text": "---- /spring-boot-101 ----\ntitle: Spring Boot 101\nimage: images/boot1.jpg\ndate: 2017-06-28\ntemplate: post\n\n# What is a Spring Bean really?\n\nToday I was feeling rather lost in my attempts to understand what is going on inside a Spring Boot application.\n\nBeing new to Spring, I had spent a fair bit of time googling and reading, but most of the things i came across simply assume prior knowledge when it comes to fundamental concepts like 'Beans'.\n\nMark Fisher, my friend and colleague here on the Spring team at Pivotal, came to my rescue and offered to explain. In exchange, I promised to write about it.\n\nThe result is this blog post and https://github.com/markfisher/spring-boot-hello-world.\n\n## In the beginning there was XML\n\nSpring started by providing a much-simpler-than-J2EE, XML-based way to configure the main classes that your Java application depended on.\n\nSimply instantiating everything with `new` in Java was not ideal because this meant that you had to hardwire all those dependencies into your code, so you couldn't easily use say one database for local testing and a different database for CI or production.  \n\nInstead of writing your own factories which abstracted the creation of things like database connections, you could use Spring and provide the details of all those things in XML.\n\nSpring would read some environment-specific XML at startup and create instances of those classes based on what was in the XML.\n\nAnd those instances were... _**Beans**_, something like this:\n\n![ApplicationContext.getBean()](/images/boot1b.jpg)\n\n## Now there are @Annotations\n\nFast forward a few years and the XML has been replaced by Java code annotated as `@Configuration` and `@ConfigurationProperties`.\n\n```java\n@Configuration\n@EnableConfigurationProperties(GreeterProperties.class)\npublic class GreeterAutoConfiguration {\n\n\t@Bean\n\tpublic Greeter greeter(GreeterProperties properties) {\n\t\treturn new Greeter(properties.getGreeting());\n\t}\n}\n```\n\n\nNotice that the factory method is annotated as `@Bean`.\n\nIf the configuration class is included in the `META-INF/spring.factories` of a dependent jar, then a Spring Boot application will automatically call the factory method to create a singleton instance of that class on startup.\n\n> This is the magic  \n> and those instances are still called **Beans**\n\n## What about [Spring Initializr](https://start.spring.io/) and all those starters?\n\nNow that [_configuration scanning_](http://docs.spring.io/spring-boot/docs/current/reference/htmlsingle/#using-boot-configuration-classes) is no longer such a mystery, the role of Spring Boot Starters is easier to understand.\n\nBy including a starter in the dependencies of your Boot App, you are telling Spring to scan for configuration classes inside that starter, which results in the automatic creation of the **Beans** for that starter.\n\n![Initializr injection](/images/boot6.jpg)\n\n> Easy!  \n> _!lemon-o_\n\n---\n\n\n---- #excerpt ----\n\nSpring Beans are magic - but what's behind them and why are they called beans?\n"
        }
      ]
    },
    {
      "path": "/Users/jleschner/pub/firstinthecloud/node_modules/pub-theme-pubblog/templates",
      "_pkg": "pub-theme-pubblog",
      "name": "templates",
      "type": "FILE",
      "watch": false,
      "files": [
        {
          "path": "/default.hbs",
          "text": "{{{html}}}\n"
        },
        {
          "path": "/doc-layout.hbs",
          "text": "<!DOCTYPE html>\n<html>\n<head>\n<meta charset=\"utf-8\">\n<meta name=\"viewport\" content=\"width=device-width, initial-scale=1\">\n<meta http-equiv=\"x-ua-compatible\" content=\"ie=edge\">\n{{{metaSeo}}}\n\n<!-- html generated by pub-server from markdown {{_file.path}} -->\n\n<title>{{title}}</title>\n{{{injectCss}}}\n<!--[if lt IE 9]>\n<script src=\"https://oss.maxcdn.com/html5shiv/3.7.2/html5shiv.min.js\"></script>\n<script src=\"https://oss.maxcdn.com/respond/1.4.2/respond.min.js\"></script>\n<![endif]-->\n</head>\n<body>\n\n{{{renderLayout}}}\n\n{{{injectJs}}}\n{{{comment \"copyright\"}}}\n</body>\n</html>\n"
        },
        {
          "path": "/home.hbs",
          "text": "{{#eachPost~}}\n<div class='postentry'>\n{{{permaLink}}}\n<h2>{{{pageLink}}}</h2>\n<div class=\"date\">{{date}}</div>\n{{{fragmentHtml [#excerpt]}}}\n</div>\n{{/eachPost}}\n"
        },
        {
          "path": "/main-layout.hbs",
          "text": "<header>\n<div id=\"doctitle\">{{{docTitle}}}</div>\n<div id=\"topmenu\">{{{topMenu}}}</div>\n</header>\n\n<div id=\"navicon\" onclick=\"\">{{{navIcon}}}\n<nav id=\"toc\">\n<ul>\n<li><strong>{{{linkTo '/' 'Home'}}}</strong></li>\n{{#eachPost~}}\n<li>{{{pageLink}}}</li>\n{{/eachPost~}}\n</ul>\n</nav>\n</div>\n\n<div id=\"title\" {{{title-style}}}>\n  <div class=\"title\">{{title}}</div>\n  <div class=\"subtitle\">{{subtitle}}</div>\n</div>\n\n<div id=\"main\" onclick=\"\">\n<div id=\"content\">\n\n{{{renderPage}}}\n\n<div id=\"credit\">{{{credit}}}</div>\n\n</div>\n</div>\n"
        },
        {
          "path": "/post.hbs",
          "text": "<span class=\"permalink\">{{{permaLink}}}</span><span class=\"date\">{{date}}</span>\n\n<div {{{style}}}>\n{{{html}}}\n</div>\n\n{{#eachFragment '#post'}}\n<div {{{style}}}>\n{{{html}}}\n</div>\n{{/eachFragment}}\n"
        }
      ]
    },
    {
      "path": "/Users/jleschner/pub/server/node_modules/pub-pkg-seo/src",
      "fragmentDelim": 1,
      "_pkg": "pub-pkg-seo",
      "name": "src",
      "type": "FILE",
      "watch": false,
      "files": [
        {
          "path": "/pages",
          "text": "---- /robots.txt ----\nnocrawl:1\nnolayout:1\ntemplate:robots.txt\naccess:everyone\n\n---- /sitemap.xml ----\nnocrawl:1\nnolayout:1\ntemplate:sitemap.xml\n"
        },
        {
          "path": "/robots.txt.hbs",
          "text": "user-agent: *\n{{#ifOption 'noRobots'}}\ndisallow: /\n{{else}}\nallow: /\n{{/ifOption}}\n"
        },
        {
          "path": "/sitemap.xml.hbs",
          "text": "<?xml version=\"1.0\" encoding=\"UTF-8\"?>\n<urlset xmlns=\"http://www.sitemaps.org/schemas/sitemap/0.9\">\n{{#eachPage~}}\n<url><loc>{{fqurl}}</loc></url>\n{{/eachPage}}\n</urlset>\n"
        }
      ]
    },
    {
      "path": "/Users/jleschner/pub/server/node_modules/pub-pkg-editor/src",
      "route": "/pub",
      "_pkg": "pub-pkg-editor",
      "name": "_src",
      "type": "FILE",
      "watch": false,
      "fragmentDelim": true,
      "files": [
        {
          "path": "/index.md",
          "text": "---- / ----\nname: pub-server\ndoclayout: pub/editor-layout\n"
        },
        {
          "path": "/editor-layout.hbs",
          "text": "<!DOCTYPE html>\n<html>\n<head>\n<meta charset=\"UTF-8\">\n<title>pub editor</title>\n<meta name=\"viewport\" content=\"width=device-width, initial-scale=1.0\">\n<link rel=\"stylesheet\" href=\"{{relPath}}/pub/css/normalize.css\">\n<link rel=\"stylesheet\" href=\"{{relPath}}/pub/css/editor.css\">\n<link rel=\"stylesheet\" href=\"{{relPath}}/pub/humane-js/flatty.css\">\n</head>\n<body>\n<div class=\"handle leftright\"></div>\n\n<div class=\"outer col\">\n\n<div class=\"header row\">\n  <!--div class=\"menubutton col clickable\"> ☰ </div-->\n  <div class=\"savebutton col clickable hide\" title=\"save\"> ✓ </div>\n  <div class=\"name col\"></div>\n  <div class=\"editbutton col clickable\" title=\"fragments\"> ✍ </div>\n  <!--div class=\"helpbutton col clickable\" title=\"help\"> ? </div-->\n</div>\n\n<div class=\"main row\">\n  <div class=\"editorpane left col\">\n    <div class=\"list row shadow\"></div>\n    <!--iframe class=\"form row shadow\" src=\"{{relPath}}/admin/upload\"></iframe-->\n    <textarea class=\"editor row\"></textarea></div>\n  <div class=\"previewpane right col\"><iframe class=\"preview\" src=\"{{relPath}}/\"></iframe></div>\n</div>\n\n</div>\n<script>window.pubRef = {\"href\":\"/pub/\",\"relPath\":\"..\"};</script>\n<script src=\"{{relPath}}/js/jquery-1.11.3.min.js\"></script>\n<script src=\"{{relPath}}/pub/js/editor-ui.js\"></script>\n<script src=\"{{relPath}}/pub/_generator.js\"></script>\n\n</body>\n</html>\n"
        },
        {
          "path": "/editor-updates.hbs",
          "text": "<ul>\n{{#each diffs}}\n<li title=\"{{difftext}}\" data-file=\"{{file}}\">{{diffpage}}</li>\n{{/each}}\n</ul>\n"
        },
        {
          "path": "/editor-upload.hbs",
          "text": "<!DOCTYPE html>\n<html>\n<head>\n<meta charset=\"UTF-8\">\n<title>pub editor - {{title}}</title>\n<meta name=\"viewport\" content=\"width=device-width, initial-scale=1.0\">\n<link rel=\"stylesheet\" href=\"{{relPath}}/css/normalize.css\">\n<link rel=\"stylesheet\" href=\"{{relPath}}/css/editor.css\">\n</head>\n<body>\n<div class=\"upload\">\n<h3>{{title}}</h3>\n<form method=\"POST\" enctype=\"multipart/form-data\">\n{{{html}}}\n</form>\n{{#eachUpload}}<pre>![](/images/{{{title}}}){{s3Err}}\n</pre>\n<img src=\"{{option 'fqImages'}}/images/{{title}}\"><br>\n{{option 'fqImages'}}/images/{{title}}\n{{/eachUpload}}\n</div>\n<script src=\"{{relPath}}/pub/js/jquery-1.11.3.min.js\"></script>\n</body>\n</html>\n"
        }
      ]
    }
  ],
  "staticPaths": [
    {
      "path": "/Users/jleschner/pub/firstinthecloud/images",
      "route": "/images",
      "watch": {},
      "depth": 5,
      "maxAge": "10m",
      "includeBinaries": true,
      "sendOpts": {
        "maxAge": "10m",
        "dotfiles": "ignore",
        "index": false,
        "extensions": false,
        "root": "/Users/jleschner/pub/firstinthecloud/images"
      }
    },
    {
      "path": "/Users/jleschner/pub/firstinthecloud/README.md",
      "watch": {},
      "route": "/",
      "depth": 5,
      "maxAge": "10m",
      "includeBinaries": true,
      "sendOpts": {
        "maxAge": "10m",
        "dotfiles": "ignore",
        "index": false,
        "extensions": false,
        "root": "/Users/jleschner/pub/firstinthecloud"
      }
    },
    {
      "path": "/Users/jleschner/pub/firstinthecloud/LICENSE.TXT",
      "watch": {},
      "route": "/",
      "depth": 5,
      "maxAge": "10m",
      "includeBinaries": true,
      "sendOpts": {
        "maxAge": "10m",
        "dotfiles": "ignore",
        "index": false,
        "extensions": false,
        "root": "/Users/jleschner/pub/firstinthecloud"
      }
    },
    {
      "path": "/Users/jleschner/pub/firstinthecloud/CNAME",
      "watch": {},
      "route": "/",
      "depth": 5,
      "maxAge": "10m",
      "includeBinaries": true,
      "sendOpts": {
        "maxAge": "10m",
        "dotfiles": "ignore",
        "index": false,
        "extensions": false,
        "root": "/Users/jleschner/pub/firstinthecloud"
      }
    },
    {
      "path": "/Users/jleschner/pub/firstinthecloud/.nojekyll",
      "watch": {},
      "route": "/",
      "depth": 5,
      "maxAge": "10m",
      "includeBinaries": true,
      "sendOpts": {
        "maxAge": "10m",
        "dotfiles": "ignore",
        "index": false,
        "extensions": false,
        "root": "/Users/jleschner/pub/firstinthecloud"
      }
    },
    {
      "path": "/Users/jleschner/pub/server/node_modules/pub-pkg-jquery/js/jquery-1.11.3.min.js",
      "route": "/js",
      "inject": true,
      "maxAge": "30d",
      "_pkg": "pub-pkg-jquery",
      "watch": false,
      "depth": 5,
      "includeBinaries": true,
      "sendOpts": {
        "maxAge": "30d",
        "dotfiles": "ignore",
        "index": false,
        "extensions": false,
        "root": "/Users/jleschner/pub/server/node_modules/pub-pkg-jquery/js"
      }
    },
    {
      "path": "/Users/jleschner/pub/firstinthecloud/node_modules/pub-theme-pubblog/css/pubblog.css",
      "route": "/css",
      "inject": true,
      "_pkg": "pub-theme-pubblog",
      "watch": false,
      "depth": 5,
      "maxAge": "10m",
      "includeBinaries": true,
      "sendOpts": {
        "maxAge": "10m",
        "dotfiles": "ignore",
        "index": false,
        "extensions": false,
        "root": "/Users/jleschner/pub/firstinthecloud/node_modules/pub-theme-pubblog/css"
      }
    },
    {
      "path": "/Users/jleschner/pub/firstinthecloud/node_modules/pub-theme-pubblog/images/default.jpg",
      "route": "/images",
      "_pkg": "pub-theme-pubblog",
      "watch": false,
      "depth": 5,
      "maxAge": "10m",
      "includeBinaries": true,
      "sendOpts": {
        "maxAge": "10m",
        "dotfiles": "ignore",
        "index": false,
        "extensions": false,
        "root": "/Users/jleschner/pub/firstinthecloud/node_modules/pub-theme-pubblog/images"
      }
    },
    {
      "path": "/Users/jleschner/pub/server/node_modules/pub-pkg-font-open-sans/open-sans.css",
      "route": "/css",
      "inject": true,
      "_pkg": "pub-pkg-font-open-sans",
      "watch": false,
      "depth": 5,
      "maxAge": "10m",
      "includeBinaries": true,
      "sendOpts": {
        "maxAge": "10m",
        "dotfiles": "ignore",
        "index": false,
        "extensions": false,
        "root": "/Users/jleschner/pub/server/node_modules/pub-pkg-font-open-sans"
      }
    },
    {
      "path": "/Users/jleschner/pub/server/node_modules/pub-pkg-font-open-sans/node_modules/open-sans-fontface/fonts",
      "route": "/css/fonts",
      "glob": "**/*.{eot,woff,woff2}",
      "maxAge": "1000d",
      "_pkg": "pub-pkg-font-open-sans",
      "watch": false,
      "depth": 5,
      "includeBinaries": true,
      "sendOpts": {
        "maxAge": "1000d",
        "dotfiles": "ignore",
        "index": false,
        "extensions": false,
        "root": "/Users/jleschner/pub/server/node_modules/pub-pkg-font-open-sans/node_modules/open-sans-fontface/fonts"
      }
    },
    {
      "path": "/Users/jleschner/pub/server/node_modules/pub-pkg-font-awesome/fonts",
      "route": "/fonts",
      "_pkg": "pub-pkg-font-awesome",
      "watch": false,
      "depth": 5,
      "maxAge": "10m",
      "includeBinaries": true,
      "sendOpts": {
        "maxAge": "10m",
        "dotfiles": "ignore",
        "index": false,
        "extensions": false,
        "root": "/Users/jleschner/pub/server/node_modules/pub-pkg-font-awesome/fonts"
      }
    },
    {
      "path": "/Users/jleschner/pub/server/node_modules/pub-pkg-font-awesome/css/font-awesome.css",
      "route": "/css",
      "inject": true,
      "_pkg": "pub-pkg-font-awesome",
      "watch": false,
      "depth": 5,
      "maxAge": "10m",
      "includeBinaries": true,
      "sendOpts": {
        "maxAge": "10m",
        "dotfiles": "ignore",
        "index": false,
        "extensions": false,
        "root": "/Users/jleschner/pub/server/node_modules/pub-pkg-font-awesome/css"
      }
    },
    {
      "path": "/Users/jleschner/pub/firstinthecloud/node_modules/pub-pkg-highlight/css/highlight-github-0.2.3.css",
      "route": "/css",
      "inject": true,
      "maxAge": "30d",
      "_pkg": "pub-pkg-highlight",
      "watch": false,
      "depth": 5,
      "includeBinaries": true,
      "sendOpts": {
        "maxAge": "30d",
        "dotfiles": "ignore",
        "index": false,
        "extensions": false,
        "root": "/Users/jleschner/pub/firstinthecloud/node_modules/pub-pkg-highlight/css"
      }
    },
    {
      "path": "/Users/jleschner/pub/firstinthecloud/node_modules/pub-pkg-highlight/js/highlight-0.2.3.min.js",
      "route": "/js",
      "inject": true,
      "maxAge": "30d",
      "_pkg": "pub-pkg-highlight",
      "watch": false,
      "depth": 5,
      "includeBinaries": true,
      "sendOpts": {
        "maxAge": "30d",
        "dotfiles": "ignore",
        "index": false,
        "extensions": false,
        "root": "/Users/jleschner/pub/firstinthecloud/node_modules/pub-pkg-highlight/js"
      }
    },
    {
      "path": "/Users/jleschner/pub/firstinthecloud/node_modules/pub-pkg-highlight/js/pub-pkg-highlight-0.2.3.js",
      "route": "/js",
      "inject": true,
      "maxAge": "30d",
      "_pkg": "pub-pkg-highlight",
      "watch": false,
      "depth": 5,
      "includeBinaries": true,
      "sendOpts": {
        "maxAge": "30d",
        "dotfiles": "ignore",
        "index": false,
        "extensions": false,
        "root": "/Users/jleschner/pub/firstinthecloud/node_modules/pub-pkg-highlight/js"
      }
    },
    {
      "path": "/Users/jleschner/pub/server/node_modules/pub-pkg-editor/static/css",
      "route": "/pub/css",
      "_pkg": "pub-pkg-editor",
      "watch": false,
      "depth": 5,
      "maxAge": "10m",
      "includeBinaries": true,
      "sendOpts": {
        "maxAge": "10m",
        "dotfiles": "ignore",
        "index": false,
        "extensions": false,
        "root": "/Users/jleschner/pub/server/node_modules/pub-pkg-editor/static/css"
      }
    },
    {
      "path": "/Users/jleschner/pub/server/node_modules/pub-pkg-editor/node_modules/humane-js/themes/flatty.css",
      "route": "/pub/humane-js",
      "_pkg": "pub-pkg-editor",
      "watch": false,
      "depth": 5,
      "maxAge": "10m",
      "includeBinaries": true,
      "sendOpts": {
        "maxAge": "10m",
        "dotfiles": "ignore",
        "index": false,
        "extensions": false,
        "root": "/Users/jleschner/pub/server/node_modules/pub-pkg-editor/node_modules/humane-js/themes"
      }
    }
  ],
  "outputs": [
    {
      "path": "/Users/jleschner/pub/firstinthecloud/docs",
      "relPaths": true,
      "name": "docs",
      "writable": true,
      "type": "FILE",
      "tmp": "/Users/jleschner/.tmp/docs",
      "watch": {}
    }
  ],
  "browserScripts": [
    {
      "path": "/Users/jleschner/pub/server/node_modules/pub-pkg-editor/client/editor-ui.js",
      "route": "/pub/js/editor-ui.js",
      "_pkg": "pub-pkg-editor"
    },
    {
      "path": "/Users/jleschner/pub/preview/pub-preview.js",
      "route": "/pub/js/pub-preview.js",
      "_pkg": "pub-pkg-editor"
    }
  ],
  "generatorPlugins": [
    {
      "path": "/Users/jleschner/pub/server/node_modules/pub-pkg-seo/generator-plugin.js",
      "_pkg": "pub-pkg-seo"
    },
    {
      "path": "/Users/jleschner/pub/server/node_modules/pub-pkg-font-awesome/generator-plugin.js",
      "_pkg": "pub-pkg-font-awesome"
    },
    {
      "path": "/Users/jleschner/pub/firstinthecloud/node_modules/pub-theme-pubblog/plugins/generator-plugin.js",
      "_pkg": "pub-theme-pubblog"
    }
  ],
  "serverPlugins": [],
  "injectCss": [
    {
      "path": "/css/pubblog.css"
    },
    {
      "path": "/css/open-sans.css"
    },
    {
      "path": "/css/font-awesome.css"
    },
    {
      "path": "/css/highlight-github-0.2.3.css"
    }
  ],
  "injectJs": [
    {
      "path": "/js/jquery-1.11.3.min.js"
    },
    {
      "path": "/js/highlight-0.2.3.min.js"
    },
    {
      "path": "/js/pub-pkg-highlight-0.2.3.js"
    },
    {
      "path": "/pub/pub-ux.js"
    }
  ],
  "pkgs": [
    {
      "path": "pub-pkg-jquery",
      "pkgJson": {
        "name": "pub-pkg-jquery",
        "version": "1.11.3",
        "description": "pub-server package to inject jQuery",
        "main": "pub-config.js",
        "dependencies": {},
        "keywords": [
          "publish",
          "jquery"
        ],
        "repository": {
          "type": "git",
          "url": "git://github.com/jldec/pub-pkg-jquery.git"
        },
        "author": "jurgen leschner",
        "license": "MIT"
      },
      "pkgName": "pub-pkg-jquery",
      "dir": "/Users/jleschner/pub/server/node_modules/pub-pkg-jquery"
    },
    {
      "path": "pub-theme-pubblog",
      "pkgJson": {
        "name": "pub-theme-pubblog",
        "version": "1.2.2",
        "description": "pub-server blogging theme",
        "main": "pub-config.js",
        "dependencies": {},
        "keywords": [
          "publish",
          "markdown",
          "pubblog"
        ],
        "repository": {
          "type": "git",
          "url": "git://github.com/jldec/pub-theme-pubblog.git"
        },
        "author": "jurgen leschner",
        "license": "MIT"
      },
      "pkgName": "pub-theme-pubblog",
      "dir": "/Users/jleschner/pub/firstinthecloud/node_modules/pub-theme-pubblog"
    },
    {
      "path": "pub-pkg-font-open-sans",
      "pkgJson": {
        "name": "pub-pkg-font-open-sans",
        "version": "1.4.1",
        "description": "pub-server package for publishing with the Open Sans font",
        "main": "pub-config.js",
        "dependencies": {
          "open-sans-fontface": "^1.4.0"
        },
        "devDependencies": {
          "pub-pkg-show-font": "^1.0.0"
        },
        "keywords": [
          "pub-server",
          "publish",
          "markdown",
          "font",
          "open-sans"
        ],
        "repository": {
          "type": "git",
          "url": "git://github.com/jldec/pub-pkg-font-open-sans.git"
        },
        "scripts": {
          "readme": "pub",
          "docedit": "pub doc",
          "docout": "pub -O doc",
          "docview": "pub -S doc/gh-pages doc"
        },
        "author": "jurgen leschner",
        "license": "MIT AND Apache-2.0"
      },
      "pkgName": "pub-pkg-font-open-sans",
      "dir": "/Users/jleschner/pub/server/node_modules/pub-pkg-font-open-sans"
    },
    {
      "path": "pub-pkg-font-awesome",
      "pkgJson": {
        "name": "pub-pkg-font-awesome",
        "version": "2.2.0",
        "description": "Use Font Awesome v4.4.0 glyphs from pub-server markdown",
        "main": "pub-config.js",
        "dependencies": {},
        "devDependencies": {},
        "keywords": [
          "publish",
          "markdown",
          "icon",
          "font",
          "awesome"
        ],
        "repository": {
          "type": "git",
          "url": "git://github.com/jldec/pub-pkg-font-awesome.git"
        },
        "scripts": {
          "readme": "pub",
          "docedit": "pub doc",
          "docout": "pub -O doc",
          "docview": "pub -S doc/gh-pages doc"
        },
        "author": "jurgen leschner",
        "license": "MIT AND OFL-1.1"
      },
      "pkgName": "pub-pkg-font-awesome",
      "dir": "/Users/jleschner/pub/server/node_modules/pub-pkg-font-awesome"
    },
    {
      "path": "pub-pkg-seo",
      "pkgJson": {
        "name": "pub-pkg-seo",
        "version": "1.0.1",
        "description": "pub-server package for generating robots.txt and sitemap.xml",
        "main": "pub-config.js",
        "dependencies": {},
        "keywords": [
          "publish",
          "seo",
          "robots",
          "sitemap"
        ],
        "repository": {
          "type": "git",
          "url": "git://github.com/jldec/pub-pkg-seo.git"
        },
        "author": "jurgen leschner",
        "license": "MIT"
      },
      "pkgName": "pub-pkg-seo",
      "dir": "/Users/jleschner/pub/server/node_modules/pub-pkg-seo"
    },
    {
      "path": "pub-pkg-highlight",
      "pkgJson": {
        "_args": [
          [
            {
              "raw": "pub-pkg-highlight@^0.2.4",
              "scope": null,
              "escapedName": "pub-pkg-highlight",
              "name": "pub-pkg-highlight",
              "rawSpec": "^0.2.4",
              "spec": ">=0.2.4 <0.3.0",
              "type": "range"
            },
            "/Users/jleschner/pub/firstinthecloud"
          ]
        ],
        "_from": "pub-pkg-highlight@>=0.2.4 <0.3.0",
        "_id": "pub-pkg-highlight@0.2.4",
        "_inCache": true,
        "_location": "/pub-pkg-highlight",
        "_nodeVersion": "2.3.4",
        "_npmUser": {
          "name": "jldec",
          "email": "jldec@ciaosoft.com"
        },
        "_npmVersion": "2.12.1",
        "_phantomChildren": {},
        "_requested": {
          "raw": "pub-pkg-highlight@^0.2.4",
          "scope": null,
          "escapedName": "pub-pkg-highlight",
          "name": "pub-pkg-highlight",
          "rawSpec": "^0.2.4",
          "spec": ">=0.2.4 <0.3.0",
          "type": "range"
        },
        "_requiredBy": [
          "/"
        ],
        "_resolved": "https://registry.npmjs.org/pub-pkg-highlight/-/pub-pkg-highlight-0.2.4.tgz",
        "_shasum": "4e68492ce6533d3afaa957e7aee12fd4af69fe78",
        "_shrinkwrap": null,
        "_spec": "pub-pkg-highlight@^0.2.4",
        "_where": "/Users/jleschner/pub/firstinthecloud",
        "author": {
          "name": "jurgen leschner"
        },
        "bugs": {
          "url": "https://github.com/jldec/pub-pkg-highlight/issues"
        },
        "dependencies": {},
        "description": "pub-server package for injecting highlight.js",
        "devDependencies": {},
        "directories": {},
        "dist": {
          "shasum": "4e68492ce6533d3afaa957e7aee12fd4af69fe78",
          "tarball": "https://registry.npmjs.org/pub-pkg-highlight/-/pub-pkg-highlight-0.2.4.tgz"
        },
        "gitHead": "4b555a4f5fed8f1d12e92ff8dbc53ed7beb3836c",
        "homepage": "https://github.com/jldec/pub-pkg-highlight#readme",
        "keywords": [
          "publish",
          "syntax",
          "highlight"
        ],
        "license": "MIT",
        "main": "pub-config.js",
        "maintainers": [
          {
            "name": "jldec",
            "email": "jldec@ciaosoft.com"
          }
        ],
        "name": "pub-pkg-highlight",
        "optionalDependencies": {},
        "readme": "ERROR: No README data found!",
        "repository": {
          "type": "git",
          "url": "git://github.com/jldec/pub-pkg-highlight.git"
        },
        "scripts": {},
        "version": "0.2.4"
      },
      "pkgName": "pub-pkg-highlight",
      "dir": "/Users/jleschner/pub/firstinthecloud/node_modules/pub-pkg-highlight"
    },
    {
      "path": "pub-pkg-editor",
      "pkgJson": {
        "name": "pub-pkg-editor",
        "version": "1.5.3",
        "description": "simple markdown editor for pub-server",
        "main": "pub-config.js",
        "dependencies": {
          "humane-js": "^3.2.2",
          "pub-preview": "^1.3.1"
        },
        "devDependencies": {},
        "repository": {
          "type": "git",
          "url": "git://github.com/jldec/pub-pkg-editor.git"
        },
        "author": "jurgen leschner",
        "license": "MIT"
      },
      "pkgName": "pub-pkg-editor",
      "dir": "/Users/jleschner/pub/server/node_modules/pub-pkg-editor"
    }
  ],
  "docTitle": "firstinthecloud",
  "appUrl": "https://firstinthecloud.com/",
  "noRobots": false,
  "throttleReload": "1s",
  "linkNewWindow": true,
  "github": "https://github.com/jldec/firstinthecloud.com",
  "theme": {
    "path": "pub-theme-pubblog",
    "pkgJson": {
      "name": "pub-theme-pubblog",
      "version": "1.2.2",
      "description": "pub-server blogging theme",
      "main": "pub-config.js",
      "dependencies": {},
      "keywords": [
        "publish",
        "markdown",
        "pubblog"
      ],
      "repository": {
        "type": "git",
        "url": "git://github.com/jldec/pub-theme-pubblog.git"
      },
      "author": "jurgen leschner",
      "license": "MIT"
    },
    "pkgName": "pub-theme-pubblog",
    "dir": "/Users/jleschner/pub/firstinthecloud/node_modules/pub-theme-pubblog"
  },
  "_resolved": true,
  "production": false,
  "port": "3001",
  "fqImages": "",
  "staticHost": true
}
